Workbook

Sheet Read Me
A1: 3-Statement Financial Model — Arjun Steel & Engineering Ltd
A2: Day 21 · 30 Days of AI Finance · Week 3 Closer · ₹ Crores
A5: WHAT THIS IS
A6: An integrated 3-Statement Financial Model — the foundation of all corporate finance work.
A7: The Income Statement, Balance Sheet, and Cash Flow Statement are fully linked:
A8: Net Income → Retained Earnings → Equity on the Balance Sheet
A9: D&A → Accumulated Depreciation → Net PP&E on the Balance Sheet
A10: Ending Cash on Cash Flow Statement = Cash on Balance Sheet
A11: The Balance Sheet balances (Assets = Liabilities + Equity) in every year — verified by CHECK row
A13: WHY THIS MODEL IS DIFFERENT
A14: 1. Fully integrated — all three statements genuinely linked, not independent tables
A15: 2. WSP-standard color coding: Blue=input, Black=formula, Green=cross-sheet link
... A49: that you haven't accidentally overwritten a formula cell (blue cells only are safe to edit).

Sheet Assumptions
A1: Model Assumptions — Arjun Steel & Engineering Ltd
A2: Blue cells are inputs. All other sheets link to this sheet.
B4: Y0 (Base) | C4: Y1 | D4: Y2 | E4: Y3 | F4: Y4 | G4: Y5 | I4: Notes
A6: P&L DRIVERS
A7: Revenue Growth % | B7: 0.12 | C7: 0.12 | D7: 0.11 | E7: 0.1 | F7: 0.09 | G7: 0.08 | I7: YoY growth
A8: COGS % of Revenue | B8: 0.71 | C8: 0.7 | D8: 0.695 | E8: 0.69 | F8: 0.685 | G8: 0.68 | I8: Gross margin driver
A9: R&D % of Revenue | B9: 0.01 | C9: 0.01 | D9: 0.01 | E9: 0.01 | F9: 0.01 | G9: 0.01
A10: SG&A % of Revenue | B10: 0.1 | C10: 0.098 | D10: 0.095 | E10: 0.093 | F10: 0.091 | G10: 0.09
A11: EBITDA Margin % (check) | B11: 0.18 | C11: 0.19 | D11: 0.2 | E11: 0.21 | F11: 0.21 | G11: 0.22 | I11: Derived — verify vs above
A12: D&A % of Revenue | B12: 0.05 | C12: 0.048 | D12: 0.047 | E12: 0.046 | F12: 0.045 | G12: 0.044 | I12: Applies to IS; PP&E schedule drives BS
A13: Tax Rate | B13: 0.25 | C13: 0.25 | D13: 0.25 | E13: 0.25 | F13: 0.25 | G13: 0.25 | I13: Indian new regime corporate tax
A15: BALANCE SHEET DRIVERS
A16: Receivables Days | B16: 65 | C16: 65 | D16: 65 | E16: 65 | F16: 65 | G16: 65 | I16: Revenue / 365 × days
A17: Inventory Days | B17: 77 | C17: 77 | D17: 77 | E17: 77 | F17: 77 | G17: 77 | I17: COGS / 365 × days
A18: Payables Days | B18: 61 | C18: 61 | D18: 61 | E18: 61 | F18: 61 | G18: 61 | I18: COGS / 365 × days
A19: Minimum Cash Balance | B19: 40 | C19: 40 | D19: 40 | E19: 40 | F19: 40 | G19: 40 | I19: Cash floor; revolver draws if needed
A21: PP&E SCHEDULE
A22: Capex % of Revenue | B22: 0.08 | C22: 0.072 | D22: 0.068 | E22: 0.065 | F22: 0.062 | G22: 0.06
A23: Depreciation Life (yrs) | B23: 15 | C23: 15 | D23: 15 | E23: 15 | F23: 15 | G23: 15 | I23: Straight-line; D&A = Gross PP&E / life
A25: DEBT & FINANCING
A26: Interest Rate on Debt | B26: 0.09 | C26: 0.09 | D26: 0.09 | E26: 0.09 | F26: 0.09 | G26: 0.09 | I26: Applied to avg debt balance
A27: Mandatory Debt Repayment | B27: 25 | C27: 25 | D27: 25 | E27: 25 | F27: 25 | G27: 25 | I27: ₹ Cr per year, senior term loan
A30: Company: Arjun Steel & Engineering Ltd — FICTIONAL. Not a real company. Not investment advice.

Sheet Income Stmt
A1: Income Statement — Arjun Steel & Engineering Ltd
A2: ₹ Crores · Sign Convention: Income +, Expenses − (WSP Conv. 1)
B4: Y0 (Base) | C4: Y1 | D4: Y2 | E4: Y3 | F4: Y4 | G4: Y5
A6: REVENUE
A7: Revenue | B7: 600 | C7: =B7*(1+Assumptions!C7) -> 672 | D7: =C7*(1+Assumptions!D7) -> 745.92 | E7: =D7*(1+Assumptions!E7) -> 820.512 | F7: =E7*(1+Assumptions!F7) -> 894.35808 | G7: =F7*(1+Assumptions!G7) -> 965.90673
A9: COGS | B9: -426 | C9: =-C7*Assumptions!C8 -> -470.4 | D9: =-D7*Assumptions!D8 -> -518.4144 | E9: =-E7*Assumptions!E8 -> -566.15328 | F9: =-F7*Assumptions!F8 -> -612.63528 | G9: =-G7*Assumptions!G8 -> -656.81657
A10: Gross Profit | B10: =B7+B9 -> 174 | C10: =C7+C9 -> 201.6 | D10: =D7+D9 -> 227.5056 | E10: =E7+E9 -> 254.35872 | F10: =F7+F9 -> 281.7228 | G10: =G7+G9 -> 309.09015
A11: Gross Margin % | B11: =B10/B7 -> 0.29 | C11: =C10/C7 -> 0.3 | D11: =D10/D7 -> 0.305 | E11: =E10/E7 -> 0.31 | F11: =F10/F7 -> 0.315 | G11: =G10/G7 -> 0.32
A13: OPERATING EXPENSES
A14: R&D Expense | B14: -6 | C14: =-C7*Assumptions!C9 -> -6.72 | D14: =-D7*Assumptions!D9 -> -7.4592 | E14: =-E7*Assumptions!E9 -> -8.20512 | F14: =-F7*Assumptions!F9 -> -8.9435808 | G14: =-G7*Assumptions!G9 -> -9.6590673
A15: SG&A Expense | B15: -60 | C15: =-C7*Assumptions!C10 -> -65.856 | D15: =-D7*Assumptions!D10 -> -70.8624 | E15: =-E7*Assumptions!E10 -> -76.307616 | F15: =-F7*Assumptions!F10 -> -81.386585 | G15: =-G7*Assumptions!G10 -> -86.931605
A16: EBITDA | B16: =B10+B14+B15 -> 108 | C16: =C10+C14+C15 -> 129.024 | D16: =D10+D14+D15 -> 149.184 | E16: =E10+E14+E15 -> 169.84598 | F16: =F10+F14+F15 -> 191.39263 | G16: =G10+G14+G15 -> 212.49948
A17: EBITDA Margin % | B17: =B16/B7 -> 0.18 | C17: =C16/C7 -> 0.192 | D17: =D16/D7 -> 0.2 | E17: =E16/E7 -> 0.207 | F17: =F16/F7 -> 0.214 | G17: =G16/G7 -> 0.22
A19: D&A (from PP&E Schedule) | B19: -30 | C19: =-'PP&E Schedule'!C14 -> -32.256 | D19: =-'PP&E Schedule'!D14 -> -35.05824 | E19: =-'PP&E Schedule'!E14 -> -37.743552 | F19: =-'PP&E Schedule'!F14 -> -40.246114 | G19: =-'PP&E Schedule'!G14 -> -42.499896
A20: EBIT (Operating Income) | B20: =B16+B19 -> 78 | C20: =C16+C19 -> 96.768 | D20: =D16+D19 -> 114.12576 | E20: =E16+E19 -> 132.10243 | F20: =F16+F19 -> 151.14652 | G20: =G16+G19 -> 169.99958
A21: EBIT Margin % | B21: =B20/B7 -> 0.13 | C21: =C20/C7 -> 0.144 | D21: =D20/D7 -> 0.153 | E21: =E20/E7 -> 0.161 | F21: =F20/F7 -> 0.169 | G21: =G20/G7 -> 0.176
A23: BELOW THE LINE
A24: Interest Expense (from Debt Schedule) | B24: -18 | C24: =-'Debt Schedule'!C16 -> -14.625 | D24: =-'Debt Schedule'!D16 -> -12.375 | E24: =-'Debt Schedule'!E16 -> -10.125 | F24: =-'Debt Schedule'!F16 -> -7.875 | G24: =-'Debt Schedule'!G16 -> -5.625
A25: Other Income / (Expense) | B25: 2 | C25: 1 | D25: 1 | E25: 1 | F25: 1 | G25: 1
A26: EBT (Pre-Tax Income) | B26: =B20+B24+B25 -> 62 | C26: =C20+C24+C25 -> 83.143 | D26: =D20+D24+D25 -> 102.75076 | E26: =E20+E24+E25 -> 122.97743 | F26: =F20+F24+F25 -> 144.27152 | G26: =G20+G24+G25 -> 165.37458
A27: Income Tax (25%) | B27: -15.5 | C27: =MIN(0,-C26*Assumptions!$B$13) -> -20.78575 | D27: =MIN(0,-D26*Assumptions!$B$13) -> -25.68769 | E27: =MIN(0,-E26*Assumptions!$B$13) -> -30.744358 | F27: =MIN(0,-F26*Assumptions!$B$13) -> -36.067879 | G27: =MIN(0,-G26*Assumptions!$B$13) -> -41.343646
A28: Net Income | B28: =B26+B27 -> 46.5 | C28: =C26+C27 -> 62.35725 | D28: =D26+D27 -> 77.06307 | E28: =E26+E27 -> 92.233074 | F28: =F26+F27 -> 108.20364 | G28: =G26+G27 -> 124.03094
A29: Net Margin % | B29: =B28/B7 -> 0.0775 | C29: =C28/C7 -> 0.092793527 | D29: =D28/D7 -> 0.10331278 | E29: =E28/E7 -> 0.11240917 | F29: =F28/F7 -> 0.12098469 | G29: =G28/G7 -> 0.12840881

Sheet PP&E Schedule
A1: PP&E Roll-Forward Schedule — Arjun Steel & Engineering Ltd
A2: BASE Method: Beginning + Additions − Disposals = Ending · ₹ Crores
B4: Y0 (Base) | C4: Y1 | D4: Y2 | E4: Y3 | F4: Y4 | G4: Y5
A6: GROSS PP&E (AT COST)
A7: Opening Gross PP&E | B7: 480 | C7: =B10 -> 510 | D7: =C10 -> 558.384 | E7: =D10 -> 609.10656 | F7: =E10 -> 662.43984 | G7: =F10 -> 717.89004
A8: Add: Capex | B8: 30 | C8: ='Income Stmt'!C7*Assumptions!C22 -> 48.384 | D8: ='Income Stmt'!D7*Assumptions!D22 -> 50.72256 | E8: ='Income Stmt'!E7*Assumptions!E22 -> 53.33328 | F8: ='Income Stmt'!F7*Assumptions!F22 -> 55.450201 | G8: ='Income Stmt'!G7*Assumptions!G22 -> 57.954404
A9: Less: Disposals (assume nil) | B9: 0 | C9: 0 | D9: 0 | E9: 0 | F9: 0 | G9: 0
A10: Closing Gross PP&E | B10: =B7+B8+B9 -> 510 | C10: =C7+C8+C9 -> 558.384 | D10: =D7+D8+D9 -> 609.10656 | E10: =E7+E8+E9 -> 662.43984 | F10: =F7+F8+F9 -> 717.89004 | G10: =G7+G8+G9 -> 775.84444
A12: ACCUMULATED DEPRECIATION
A13: Opening Accum. Depreciation | B13: 150 | C13: =B16 -> 180 | D13: =C16 -> 212.256 | E13: =D16 -> 247.31424 | F13: =E16 -> 285.05779 | G13: =F16 -> 325.30391
A14: Add: Depreciation Charge | B14: 30 | C14: ='Income Stmt'!C7*Assumptions!C12 -> 32.256 | D14: ='Income Stmt'!D7*Assumptions!D12 -> 35.05824 | E14: ='Income Stmt'!E7*Assumptions!E12 -> 37.743552 | F14: ='Income Stmt'!F7*Assumptions!F12 -> 40.246114 | G14: ='Income Stmt'!G7*Assumptions!G12 -> 42.499896
A15: Less: Accum Dep on Disposals | B15: 0 | C15: 0 | D15: 0 | E15: 0 | F15: 0 | G15: 0
A16: Closing Accum. Depreciation | B16: =B13+B14-B15 -> 180 | C16: =C13+C14-C15 -> 212.256 | D16: =D13+D14-D15 -> 247.31424 | E16: =E13+E14-E15 -> 285.05779 | F16: =F13+F14-F15 -> 325.30391 | G16: =G13+G14-G15 -> 367.8038
A18: NET PP&E (for Balance Sheet)
A19: Net PP&E = Gross − Accum Dep | B19: =B10-B16 -> 330 | C19: =C10-C16 -> 346.128 | D19: =D10-D16 -> 361.79232 | E19: =E10-E16 -> 377.38205 | F19: =F10-F16 -> 392.58614 | G19: =G10-G16 -> 408.04064

Sheet Debt Schedule
A1: Debt Schedule — Arjun Steel & Engineering Ltd
A2: ₹ Crores · Interest on average debt balance · Senior Term Loan
B4: Y0 (Base) | C4: Y1 | D4: Y2 | E4: Y3 | F4: Y4 | G4: Y5
A6: SENIOR TERM LOAN
A7: Opening Debt Balance | B7: 200 | C7: =B11 -> 175 | D7: =C11 -> 150 | E7: =D11 -> 125 | F7: =E11 -> 100 | G7: =F11 -> 75
A8: Add: New Borrowings | B8: 0 | C8: 0 | D8: 0 | E8: 0 | F8: 0 | G8: 0
A9: Less: Mandatory Repayment | B9: -25 | C9: =-Assumptions!C27 -> -25 | D9: =-Assumptions!D27 -> -25 | E9: =-Assumptions!E27 -> -25 | F9: =-Assumptions!F27 -> -25 | G9: =-Assumptions!G27 -> -25
A10: Add: Cash Sweep (excess cash) | B10: 0 | C10: 0 | D10: 0 | E10: 0 | F10: 0 | G10: 0
A11: Closing Debt Balance | B11: =MAX(0,B7+B8+B9+B10) -> 175 | C11: =MAX(0,C7+C8+C9+C10) -> 150 | D11: =MAX(0,D7+D8+D9+D10) -> 125 | E11: =MAX(0,E7+E8+E9+E10) -> 100 | F11: =MAX(0,F7+F8+F9+F10) -> 75 | G11: =MAX(0,G7+G8+G9+G10) -> 50
A13: INTEREST EXPENSE
A14: Average Debt Balance | B14: 200 | C14: =AVERAGE(B11,C11) -> 162.5 | D14: =AVERAGE(C11,D11) -> 137.5 | E14: =AVERAGE(D11,E11) -> 112.5 | F14: =AVERAGE(E11,F11) -> 87.5 | G14: =AVERAGE(F11,G11) -> 62.5
A15: Interest Rate | B15: =Assumptions!$B$26 -> 0.09 | C15: =Assumptions!$B$26 -> 0.09 | D15: =Assumptions!$B$26 -> 0.09 | E15: =Assumptions!$B$26 -> 0.09 | F15: =Assumptions!$B$26 -> 0.09 | G15: =Assumptions!$B$26 -> 0.09
A16: Interest Expense (positive = expense) | B16: 18 | C16: =C14*C15 -> 14.625 | D16: =D14*D15 -> 12.375 | E16: =E14*E15 -> 10.125 | F16: =F14*F15 -> 7.875 | G16: =G14*G15 -> 5.625

Sheet Working Capital
A1: Working Capital Schedule — Arjun Steel & Engineering Ltd
A2: ₹ Crores · Receivables/Inventory increase = cash use (negative); Payables increase = cash source
B4: Y0 (Base) | C4: Y1 | D4: Y2 | E4: Y3 | F4: Y4 | G4: Y5
A6: RECEIVABLES
A7: Receivables Days | B7: =Assumptions!$B$16 -> 65 | C7: =Assumptions!$B$16 -> 65 | D7: =Assumptions!$B$16 -> 65 | E7: =Assumptions!$B$16 -> 65 | F7: =Assumptions!$B$16 -> 65 | G7: =Assumptions!$B$16 -> 65
A8: Ending Receivables | B8: 108 | C8: ='Income Stmt'!C7/365*Assumptions!$B$16 -> 119.67123 | D8: ='Income Stmt'!D7/365*Assumptions!$B$16 -> 132.83507 | E8: ='Income Stmt'!E7/365*Assumptions!$B$16 -> 146.11858 | F8: ='Income Stmt'!F7/365*Assumptions!$B$16 -> 159.26925 | G8: ='Income Stmt'!G7/365*Assumptions!$B$16 -> 172.01079
A10: INVENTORY
A11: Inventory Days | B11: =Assumptions!$B$17 -> 77 | C11: =Assumptions!$B$17 -> 77 | D11: =Assumptions!$B$17 -> 77 | E11: =Assumptions!$B$17 -> 77 | F11: =Assumptions!$B$17 -> 77 | G11: =Assumptions!$B$17 -> 77
A12: COGS (absolute, positive) | B12: 426 | C12: =-'Income Stmt'!C9 -> 470.4 | D12: =-'Income Stmt'!D9 -> 518.4144 | E12: =-'Income Stmt'!E9 -> 566.15328 | F12: =-'Income Stmt'!F9 -> 612.63528 | G12: =-'Income Stmt'!G9 -> 656.81657
A13: Ending Inventory | B13: 90 | C13: =C12/365*Assumptions!$B$17 -> 99.235068 | D13: =D12/365*Assumptions!$B$17 -> 109.36413 | E13: =E12/365*Assumptions!$B$17 -> 119.43508 | F13: =F12/365*Assumptions!$B$17 -> 129.24087 | G13: =G12/365*Assumptions!$B$17 -> 138.5613
A15: ACCOUNTS PAYABLE
A16: Payables Days | B16: =Assumptions!$B$18 -> 61 | C16: =Assumptions!$B$18 -> 61 | D16: =Assumptions!$B$18 -> 61 | E16: =Assumptions!$B$18 -> 61 | F16: =Assumptions!$B$18 -> 61 | G16: =Assumptions!$B$18 -> 61
A17: Ending Payables | B17: 71 | C17: =C12/365*Assumptions!$B$18 -> 78.614795 | D17: =D12/365*Assumptions!$B$18 -> 86.639119 | E17: =E12/365*Assumptions!$B$18 -> 94.617397 | F17: =F12/365*Assumptions!$B$18 -> 102.38562 | G17: =G12/365*Assumptions!$B$18 -> 109.76935
A19: NET WORKING CAPITAL & DELTA NWC
A20: Net Working Capital (Rec+Inv-Pay) | B20: =B8+B13-B17 -> 127 | C20: =C8+C13-C17 -> 140.29151 | D20: =D8+D13-D17 -> 155.56008 | E20: =E8+E13-E17 -> 170.93625 | F20: =F8+F13-F17 -> 186.12449 | G20: =G8+G13-G17 -> 200.80275
A21: Change in NWC (Δ NWC) | B21: 0 | C21: =-(C20-B20) -> -13.291507 | D21: =-(D20-C20) -> -15.268576 | E21: =-(E20-D20) -> -15.37617 | F21: =-(F20-E20) -> -15.188239 | G21: =-(G20-F20) -> -14.678254
A22: Note: Negative = NWC increase = cash outflow

Sheet Balance Sheet
A1: Balance Sheet — Arjun Steel & Engineering Ltd
A2: ₹ Crores · All line items linked from supporting schedules · CHECK must = 0.0 in all periods
B4: Y0 (Base) | C4: Y1 | D4: Y2 | E4: Y3 | F4: Y4 | G4: Y5
A6: CURRENT ASSETS
A7: Cash & Cash Equivalents | B7: 45 | C7: ='Cash Flow'!C29 -> 55.457743 | D7: ='Cash Flow'!D29 -> 79.176317 | E7: ='Cash Flow'!E29 -> 118.06318 | F7: ='Cash Flow'!F29 -> 173.48325 | G7: ='Cash Flow'!G29 -> 244.93307
A8: Accounts Receivable | B8: 108 | C8: ='Working Capital'!C8 -> 119.67123 | D8: ='Working Capital'!D8 -> 132.83507 | E8: ='Working Capital'!E8 -> 146.11858 | F8: ='Working Capital'!F8 -> 159.26925 | G8: ='Working Capital'!G8 -> 172.01079
A9: Inventory | B9: 90 | C9: ='Working Capital'!C13 -> 99.235068 | D9: ='Working Capital'!D13 -> 109.36413 | E9: ='Working Capital'!E13 -> 119.43508 | F9: ='Working Capital'!F13 -> 129.24087 | G9: ='Working Capital'!G13 -> 138.5613
A10: Prepaid & Other Current Assets | B10: 8 | C10: =B10 -> 8 | D10: =B10 -> 8 | E10: =B10 -> 8 | F10: =B10 -> 8 | G10: =B10 -> 8
A11: Total Current Assets | B11: =B7+B8+B9+B10 -> 251 | C11: =C7+C8+C9+C10 -> 282.36404 | D11: =D7+D8+D9+D10 -> 329.37552 | E11: =E7+E8+E9+E10 -> 391.61683 | F11: =F7+F8+F9+F10 -> 469.99337 | G11: =G7+G8+G9+G10 -> 563.50516
A13: NON-CURRENT ASSETS
A14: Net PP&E | B14: 330 | C14: ='PP&E Schedule'!C19 -> 346.128 | D14: ='PP&E Schedule'!D19 -> 361.79232 | E14: ='PP&E Schedule'!E19 -> 377.38205 | F14: ='PP&E Schedule'!F19 -> 392.58614 | G14: ='PP&E Schedule'!G19 -> 408.04064
A15: Intangible Assets & Others | B15: 20 | C15: =$B$15 -> 20 | D15: =$B$15 -> 20 | E15: =$B$15 -> 20 | F15: =$B$15 -> 20 | G15: =$B$15 -> 20
A16: Total Non-Current Assets | B16: =B14+B15 -> 350 | C16: =C14+C15 -> 366.128 | D16: =D14+D15 -> 381.79232 | E16: =E14+E15 -> 397.38205 | F16: =F14+F15 -> 412.58614 | G16: =G14+G15 -> 428.04064
A17: TOTAL ASSETS | B17: =B11+B16 -> 601 | C17: =C11+C16 -> 648.49204 | D17: =D11+D16 -> 711.16784 | E17: =E11+E16 -> 788.99888 | F17: =F11+F16 -> 882.5795 | G17: =G11+G16 -> 991.5458
A19: CURRENT LIABILITIES
A20: Accounts Payable | B20: 71 | C20: ='Working Capital'!C17 -> 78.614795 | D20: ='Working Capital'!D17 -> 86.639119 | E20: ='Working Capital'!E17 -> 94.617397 | F20: ='Working Capital'!F17 -> 102.38562 | G20: ='Working Capital'!G17 -> 109.76935
A21: Accrued Liabilities | B21: 18 | C21: ='Income Stmt'!C7*0.03 -> 20.16 | D21: ='Income Stmt'!D7*0.03 -> 22.3776 | E21: ='Income Stmt'!E7*0.03 -> 24.61536 | F21: ='Income Stmt'!F7*0.03 -> 26.830742 | G21: ='Income Stmt'!G7*0.03 -> 28.977202
A22: Current Portion of Debt | B22: 25 | C22: =Assumptions!$C$27 -> 25 | D22: =Assumptions!$C$27 -> 25 | E22: =Assumptions!$C$27 -> 25 | F22: =Assumptions!$C$27 -> 25 | G22: =Assumptions!$C$27 -> 25
A23: Total Current Liabilities | B23: =B20+B21+B22 -> 114 | C23: =C20+C21+C22 -> 123.77479 | D23: =D20+D21+D22 -> 134.01672 | E23: =E20+E21+E22 -> 144.23276 | F23: =F20+F21+F22 -> 154.21637 | G23: =G20+G21+G22 -> 163.74655
A25: NON-CURRENT LIABILITIES
A26: Long-Term Debt | B26: 150 | C26: =MAX(0,'Debt Schedule'!C11-C22) -> 125 | D26: =MAX(0,'Debt Schedule'!D11-D22) -> 100 | E26: =MAX(0,'Debt Schedule'!E11-E22) -> 75 | F26: =MAX(0,'Debt Schedule'!F11-F22) -> 50 | G26: =MAX(0,'Debt Schedule'!G11-G22) -> 25
A27: Deferred Tax Liability | B27: 12 | C27: =B27*1.03 -> 12.36 | D27: =C27*1.03 -> 12.7308 | E27: =D27*1.03 -> 13.112724 | F27: =E27*1.03 -> 13.506106 | G27: =F27*1.03 -> 13.911289
A28: Total Non-Current Liabilities | B28: =B26+B27 -> 162 | C28: =C26+C27 -> 137.36 | D28: =D26+D27 -> 112.7308 | E28: =E26+E27 -> 88.112724 | F28: =F26+F27 -> 63.506106 | G28: =G26+G27 -> 38.911289
A29: TOTAL LIABILITIES | B29: =B23+B28 -> 276 | C29: =C23+C28 -> 261.13479 | D29: =D23+D28 -> 246.74752 | E29: =E23+E28 -> 232.34548 | F29: =F23+F28 -> 217.72247 | G29: =G23+G28 -> 202.65784
A31: SHAREHOLDERS' EQUITY
A32: Share Capital | B32: 50 | C32: =B32 -> 50 | D32: =C32 -> 50 | E32: =D32 -> 50 | F32: =E32 -> 50 | G32: =F32 -> 50
A33: Retained Earnings (Opening) | B33: 275 | C33: =B36 -> 275 | D33: =C36 -> 337.35725 | E33: =D36 -> 414.42032 | F33: =E36 -> 506.65339 | G33: =F36 -> 614.85703
A34: Add: Net Income | B34: 0 | C34: ='Income Stmt'!C28 -> 62.35725 | D34: ='Income Stmt'!D28 -> 77.06307 | E34: ='Income Stmt'!E28 -> 92.233074 | F34: ='Income Stmt'!F28 -> 108.20364 | G34: ='Income Stmt'!G28 -> 124.03094
A35: Less: Dividends | B35: 0 | C35: 0 | D35: 0 | E35: 0 | F35: 0 | G35: 0
A36: Closing Retained Earnings | B36: =B33+B34+B35 -> 275 | C36: =C33+C34+C35 -> 337.35725 | D36: =D33+D34+D35 -> 414.42032 | E36: =E33+E34+E35 -> 506.65339 | F36: =F33+F34+F35 -> 614.85703 | G36: =G33+G34+G35 -> 738.88797
A37: TOTAL EQUITY | B37: =B32+B36 -> 325 | C37: =C32+C36 -> 387.35725 | D37: =D32+D36 -> 464.42032 | E37: =E32+E36 -> 556.65339 | F37: =F32+F36 -> 664.85703 | G37: =G32+G36 -> 788.88797
A38: TOTAL LIABILITIES + EQUITY | B38: =B29+B37 -> 601 | C38: =C29+C37 -> 648.49204 | D38: =D29+D37 -> 711.16784 | E38: =E29+E37 -> 788.99888 | F38: =F29+F37 -> 882.5795 | G38: =G29+G37 -> 991.5458
A40: ⚡ BALANCE CHECK (must = 0.0 in all periods) | B40: =B17-B38 -> 0 | C40: =C17-C38 -> 0 | D40: =D17-D38 -> 0 | E40: =E17-E38 -> 0 | F40: =F17-F38 -> 0 | G40: =G17-G38 -> 0
A41: If CHECK ≠ 0: a formula error exists. Cash Flow or Equity linkage is broken.

Sheet Cash Flow
A1: Cash Flow Statement — Arjun Steel & Engineering Ltd
A2: ₹ Crores · Indirect Method · Operating + Investing + Financing = Net Change in Cash
B4: Y0 (Base) | C4: Y1 | D4: Y2 | E4: Y3 | F4: Y4 | G4: Y5
A6: OPERATING ACTIVITIES
A7: Net Income | B7: 46.5 | C7: ='Income Stmt'!C28 -> 62.35725 | D7: ='Income Stmt'!D28 -> 77.06307 | E7: ='Income Stmt'!E28 -> 92.233074 | F7: ='Income Stmt'!F28 -> 108.20364 | G7: ='Income Stmt'!G28 -> 124.03094
A8: Add: D&A (non-cash) | B8: 30 | C8: ='PP&E Schedule'!C14 -> 32.256 | D8: ='PP&E Schedule'!D14 -> 35.05824 | E8: ='PP&E Schedule'!E14 -> 37.743552 | F8: ='PP&E Schedule'!F14 -> 40.246114 | G8: ='PP&E Schedule'!G14 -> 42.499896
A9: Change in Working Capital (Δ NWC) | B9: 0 | C9: ='Working Capital'!C21 -> -13.291507 | D9: ='Working Capital'!D21 -> -15.268576 | E9: ='Working Capital'!E21 -> -15.37617 | F9: ='Working Capital'!F21 -> -15.188239 | G9: ='Working Capital'!G21 -> -14.678254
A10: Change in Deferred Tax | B10: 1 | C10: ='Balance Sheet'!C27-'Balance Sheet'!B27 -> 0.36 | D10: ='Balance Sheet'!D27-'Balance Sheet'!C27 -> 0.3708 | E10: ='Balance Sheet'!E27-'Balance Sheet'!D27 -> 0.381924 | F10: ='Balance Sheet'!F27-'Balance Sheet'!E27 -> 0.39338172 | G10: ='Balance Sheet'!G27-'Balance Sheet'!F27 -> 0.40518317
A11: Change in Accrued Liabilities | B11: 1.5 | C11: ='Balance Sheet'!C21-'Balance Sheet'!B21 -> 2.16 | D11: ='Balance Sheet'!D21-'Balance Sheet'!C21 -> 2.2176 | E11: ='Balance Sheet'!E21-'Balance Sheet'!D21 -> 2.23776 | F11: ='Balance Sheet'!F21-'Balance Sheet'!E21 -> 2.2153824 | G11: ='Balance Sheet'!G21-'Balance Sheet'!F21 -> 2.1464594
A12: Cash from Operating Activities | B12: =B7+B8+B9+B10+B11 -> 79 | C12: =C7+C8+C9+C10+C11 -> 83.841743 | D12: =D7+D8+D9+D10+D11 -> 99.441134 | E12: =E7+E8+E9+E10+E11 -> 117.22014 | F12: =F7+F8+F9+F10+F11 -> 135.87028 | G12: =G7+G8+G9+G10+G11 -> 154.40422
A14: INVESTING ACTIVITIES
A15: Capital Expenditure (Capex) | B15: -45 | C15: =-'PP&E Schedule'!C8 -> -48.384 | D15: =-'PP&E Schedule'!D8 -> -50.72256 | E15: =-'PP&E Schedule'!E8 -> -53.33328 | F15: =-'PP&E Schedule'!F8 -> -55.450201 | G15: =-'PP&E Schedule'!G8 -> -57.954404
A16: Proceeds from Asset Disposals | B16: 0 | C16: 0 | D16: 0 | E16: 0 | F16: 0 | G16: 0
A17: Cash from Investing Activities | B17: =B15+B16 -> -45 | C17: =C15+C16 -> -48.384 | D17: =D15+D16 -> -50.72256 | E17: =E15+E16 -> -53.33328 | F17: =F15+F16 -> -55.450201 | G17: =G15+G16 -> -57.954404
A19: FINANCING ACTIVITIES
A20: New Debt Raised | B20: 0 | C20: 0 | D20: 0 | E20: 0 | F20: 0 | G20: 0
A21: Debt Repayment | B21: -25 | C21: ='Debt Schedule'!C9 -> -25 | D21: ='Debt Schedule'!D9 -> -25 | E21: ='Debt Schedule'!E9 -> -25 | F21: ='Debt Schedule'!F9 -> -25 | G21: ='Debt Schedule'!G9 -> -25
A22: Equity Issuance / (Buyback) | B22: 0 | C22: 0 | D22: 0 | E22: 0 | F22: 0 | G22: 0
A23: Dividends Paid | B23: =-'Balance Sheet'!B35 -> 0 | C23: =-'Balance Sheet'!C35 -> 0 | D23: =-'Balance Sheet'!D35 -> 0 | E23: =-'Balance Sheet'!E35 -> 0 | F23: =-'Balance Sheet'!F35 -> 0 | G23: =-'Balance Sheet'!G35 -> 0
A24: Cash from Financing Activities | B24: =B20+B21+B22+B23 -> -25 | C24: =C20+C21+C22+C23 -> -25 | D24: =D20+D21+D22+D23 -> -25 | E24: =E20+E21+E22+E23 -> -25 | F24: =F20+F21+F22+F23 -> -25 | G24: =G20+G21+G22+G23 -> -25
A26: NET CHANGE IN CASH
A27: Net Change in Cash | B27: =B12+B17+B24 -> 9 | C27: =C12+C17+C24 -> 10.457743 | D27: =D12+D17+D24 -> 23.718574 | E27: =E12+E17+E24 -> 38.88686 | F27: =F12+F17+F24 -> 55.420074 | G27: =G12+G17+G24 -> 71.449819
A28: Beginning Cash Balance | B28: 20 | C28: ='Balance Sheet'!B7 -> 45 | D28: ='Balance Sheet'!C7 -> 55.457743 | E28: ='Balance Sheet'!D7 -> 79.176317 | F28: ='Balance Sheet'!E7 -> 118.06318 | G28: ='Balance Sheet'!F7 -> 173.48325
A29: Ending Cash Balance | B29: 45 | C29: =MAX(Assumptions!$B$19,C28+C27) -> 55.457743 | D29: =MAX(Assumptions!$B$19,D28+D27) -> 79.176317 | E29: =MAX(Assumptions!$B$19,E28+E27) -> 118.06318 | F29: =MAX(Assumptions!$B$19,F28+F27) -> 173.48325 | G29: =MAX(Assumptions!$B$19,G28+G27) -> 244.93307
A31: FCFF = Operating CF + Interest×(1-Tax) | B31: =B12+ABS('Income Stmt'!B24)*(1-Assumptions!$B$13) -> 92.5 | C31: =C12+ABS('Income Stmt'!C24)*(1-Assumptions!$B$13) -> 94.810493 | D31: =D12+ABS('Income Stmt'!D24)*(1-Assumptions!$B$13) -> 108.72238 | E31: =E12+ABS('Income Stmt'!E24)*(1-Assumptions!$B$13) -> 124.81389 | F31: =F12+ABS('Income Stmt'!F24)*(1-Assumptions!$B$13) -> 141.77653 | G31: =G12+ABS('Income Stmt'!G24)*(1-Assumptions!$B$13) -> 158.62297
A32: FCFE = Operating CF - Capex + Net Borrowings | B32: =B12+B15+B20+B21 -> 9 | C32: =C12+C15+C20+C21 -> 10.457743 | D32: =D12+D15+D20+D21 -> 23.718574 | E32: =E12+E15+E20+E21 -> 38.88686 | F32: =F12+F15+F20+F21 -> 55.420074 | G32: =G12+G15+G20+G21 -> 71.449819

Sheet Ratios
A1: Key Financial Ratios & Credit Metrics — Arjun Steel & Engineering Ltd
A2: All ratios computed from the 3 statements. No hardcoded values.
B4: Y0 (Base) | C4: Y1 | D4: Y2 | E4: Y3 | F4: Y4 | G4: Y5
A6: PROFITABILITY RATIOS
A7: Revenue Growth % | B7: 0% | C7: ='Income Stmt'!C7/'Income Stmt'!B7-1 -> 0.12 | D7: ='Income Stmt'!D7/'Income Stmt'!C7-1 -> 0.11 | E7: ='Income Stmt'!E7/'Income Stmt'!D7-1 -> 0.1 | F7: ='Income Stmt'!F7/'Income Stmt'!E7-1 -> 0.09 | G7: ='Income Stmt'!G7/'Income Stmt'!F7-1 -> 0.08
A8: Gross Margin % | B8: ='Income Stmt'!B10/'Income Stmt'!B7 -> 0.29 | C8: ='Income Stmt'!C10/'Income Stmt'!C7 -> 0.3 | D8: ='Income Stmt'!D10/'Income Stmt'!D7 -> 0.305 | E8: ='Income Stmt'!E10/'Income Stmt'!E7 -> 0.31 | F8: ='Income Stmt'!F10/'Income Stmt'!F7 -> 0.315 | G8: ='Income Stmt'!G10/'Income Stmt'!G7 -> 0.32
A9: EBITDA Margin % | B9: ='Income Stmt'!B16/'Income Stmt'!B7 -> 0.18 | C9: ='Income Stmt'!C16/'Income Stmt'!C7 -> 0.192 | D9: ='Income Stmt'!D16/'Income Stmt'!D7 -> 0.2 | E9: ='Income Stmt'!E16/'Income Stmt'!E7 -> 0.207 | F9: ='Income Stmt'!F16/'Income Stmt'!F7 -> 0.214 | G9: ='Income Stmt'!G16/'Income Stmt'!G7 -> 0.22
A10: EBIT Margin % | B10: ='Income Stmt'!B20/'Income Stmt'!B7 -> 0.13 | C10: ='Income Stmt'!C20/'Income Stmt'!C7 -> 0.144 | D10: ='Income Stmt'!D20/'Income Stmt'!D7 -> 0.153 | E10: ='Income Stmt'!E20/'Income Stmt'!E7 -> 0.161 | F10: ='Income Stmt'!F20/'Income Stmt'!F7 -> 0.169 | G10: ='Income Stmt'!G20/'Income Stmt'!G7 -> 0.176
A11: Net Margin % | B11: ='Income Stmt'!B28/'Income Stmt'!B7 -> 0.0775 | C11: ='Income Stmt'!C28/'Income Stmt'!C7 -> 0.092793527 | D11: ='Income Stmt'!D28/'Income Stmt'!D7 -> 0.10331278 | E11: ='Income Stmt'!E28/'Income Stmt'!E7 -> 0.11240917 | F11: ='Income Stmt'!F28/'Income Stmt'!F7 -> 0.12098469 | G11: ='Income Stmt'!G28/'Income Stmt'!G7 -> 0.12840881
A13: RETURN METRICS
A14: Return on Equity (ROE) | B14: ='Income Stmt'!B28/'Balance Sheet'!B37 -> 0.14307692 | C14: ='Income Stmt'!C28/'Balance Sheet'!C37 -> 0.16098124 | D14: ='Income Stmt'!D28/'Balance Sheet'!D37 -> 0.16593389 | E14: ='Income Stmt'!E28/'Balance Sheet'!E37 -> 0.16569211 | F14: ='Income Stmt'!F28/'Balance Sheet'!F37 -> 0.16274722 | G14: ='Income Stmt'!G28/'Balance Sheet'!G37 -> 0.1572225
A15: Return on Assets (ROA) | B15: ='Income Stmt'!B28/'Balance Sheet'!B17 -> 0.077371048 | C15: ='Income Stmt'!C28/'Balance Sheet'!C17 -> 0.096157309 | D15: ='Income Stmt'!D28/'Balance Sheet'!D17 -> 0.1083613 | E15: ='Income Stmt'!E28/'Balance Sheet'!E17 -> 0.11689887 | F15: ='Income Stmt'!F28/'Balance Sheet'!F17 -> 0.12259931 | G15: ='Income Stmt'!G28/'Balance Sheet'!G17 -> 0.12508846
A16: Return on Capital Employed (ROCE) | B16: ='Income Stmt'!B20/('Balance Sheet'!B17-'Balance Sheet'!B23) -> 0.16016427 | C16: ='Income Stmt'!C20/('Balance Sheet'!C17-'Balance Sheet'!C23) -> 0.18441932 | D16: ='Income Stmt'!D20/('Balance Sheet'!D17-'Balance Sheet'!D23) -> 0.19773982 | E16: ='Income Stmt'!E20/('Balance Sheet'!E17-'Balance Sheet'!E23) -> 0.20488426 | F16: ='Income Stmt'!F20/('Balance Sheet'!F17-'Balance Sheet'!F23) -> 0.20751533 | G16: ='Income Stmt'!G20/('Balance Sheet'!G17-'Balance Sheet'!G23) -> 0.2053633
A18: CREDIT METRICS
A19: Net Debt / EBITDA | B19: =('Debt Schedule'!B11-'Balance Sheet'!B7)/'Income Stmt'!B16 -> 1.2037037 | C19: =('Debt Schedule'!C11-'Balance Sheet'!C7)/'Income Stmt'!C16 -> 0.73274939 | D19: =('Debt Schedule'!D11-'Balance Sheet'!D7)/'Income Stmt'!D16 -> 0.30716218 | E19: =('Debt Schedule'!E11-'Balance Sheet'!E7)/'Income Stmt'!E16 -> -0.10635033 | F19: =('Debt Schedule'!F11-'Balance Sheet'!F7)/'Income Stmt'!F16 -> -0.51456136 | G19: =('Debt Schedule'!G11-'Balance Sheet'!G7)/'Income Stmt'!G16 -> -0.91733434
A20: Interest Coverage (EBITDA/Interest) | B20: ='Income Stmt'!B16/'Debt Schedule'!B16 -> 6 | C20: ='Income Stmt'!C16/'Debt Schedule'!C16 -> 8.8221538 | D20: ='Income Stmt'!D16/'Debt Schedule'!D16 -> 12.055273 | E20: ='Income Stmt'!E16/'Debt Schedule'!E16 -> 16.774912 | F20: ='Income Stmt'!F16/'Debt Schedule'!F16 -> 24.303826 | G20: ='Income Stmt'!G16/'Debt Schedule'!G16 -> 37.777685
A21: Debt / Equity | B21: ='Debt Schedule'!B11/'Balance Sheet'!B37 -> 0.53846154 | C21: ='Debt Schedule'!C11/'Balance Sheet'!C37 -> 0.38723943 | D21: ='Debt Schedule'!D11/'Balance Sheet'!D37 -> 0.26915274 | E21: ='Debt Schedule'!E11/'Balance Sheet'!E37 -> 0.179645 | F21: ='Debt Schedule'!F11/'Balance Sheet'!F37 -> 0.11280621 | G21: ='Debt Schedule'!G11/'Balance Sheet'!G37 -> 0.063380356
A23: CASH FLOW METRICS
A24: FCFF (₹ Cr) | B24: ='Cash Flow'!B31 -> 92.5 | C24: ='Cash Flow'!C31 -> 94.810493 | D24: ='Cash Flow'!D31 -> 108.72238 | E24: ='Cash Flow'!E31 -> 124.81389 | F24: ='Cash Flow'!F31 -> 141.77653 | G24: ='Cash Flow'!G31 -> 158.62297
A25: FCFE (₹ Cr) | B25: ='Cash Flow'!B32 -> 9 | C25: ='Cash Flow'!C32 -> 10.457743 | D25: ='Cash Flow'!D32 -> 23.718574 | E25: ='Cash Flow'!E32 -> 38.88686 | F25: ='Cash Flow'!F32 -> 55.420074 | G25: ='Cash Flow'!G32 -> 71.449819
A26: Capex / Revenue | B26: =ABS('PP&E Schedule'!B8)/'Income Stmt'!B7 -> 0.05 | C26: =ABS('PP&E Schedule'!C8)/'Income Stmt'!C7 -> 0.072 | D26: =ABS('PP&E Schedule'!D8)/'Income Stmt'!D7 -> 0.068 | E26: =ABS('PP&E Schedule'!E8)/'Income Stmt'!E7 -> 0.065 | F26: =ABS('PP&E Schedule'!F8)/'Income Stmt'!F7 -> 0.062 | G26: =ABS('PP&E Schedule'!G8)/'Income Stmt'!G7 -> 0.06
A27: Cash Conversion (OCF/EBITDA) | B27: ='Cash Flow'!B12/'Income Stmt'!B16 -> 0.73148148 | C27: ='Cash Flow'!C12/'Income Stmt'!C16 -> 0.6498151 | D27: ='Cash Flow'!D12/'Income Stmt'!D16 -> 0.66656701 | E27: ='Cash Flow'!E12/'Income Stmt'!E16 -> 0.6901555 | F27: ='Cash Flow'!F12/'Income Stmt'!F16 -> 0.70990338 | G27: ='Cash Flow'!G12/'Income Stmt'!G16 -> 0.72660989
