Workbook

Sheet Cover
A1: CompsDesk — Comparable Company Analysis
A2: Day 19 · 30 Days of AI Finance · Indian IT Sector · FY25 Verified Data
A4: SHEET GUIDE | B4: Contents
A5: 1 · Cover | B5: Navigation and model overview
A6: 2 · Peer Data | B6: FY25 raw financials — 6 verified Indian IT peers (blue = input)
A7: 3 · Multiple Engine | B7: Computed EV/Revenue, EV/EBITDA, P/E, P/BV for all peers
A8: 4 · Statistics | B8: Min / 25th / Median / Mean / 75th / Max — full set and ex-Coforge
A9: 5 · Target | B9: Meridian Digital Ltd — fictional target company (blue = change these)
A10: 6 · Implied Valuation | B10: 4-method implied prices + football field range table
A12: HOW TO USE
A13: Change any BLUE cell — all formulas recalculate automatically.
A14: Blue = hardcoded input | Black = formula | Green = cross-sheet link
A16: DISCLAIMER
A17: Peer data FY25 verified against NSE/BSE filings. Meridian Digital Ltd is fictional. Not investment advice.

Sheet Peer Data
A1: Peer Universe — FY25 Annual Financials (INR Crores)
A2: Blue cells = hardcoded inputs · Source: NSE/BSE annual filings, company investor relations FY25
A3: Company | B3: Price (₹) | C3: Mkt Cap (Cr) | D3: Shares (Cr) | E3: Debt (Cr) | F3: Cash (Cr) | G3: Revenue (Cr) | H3: EBITDA (Cr) | I3: PAT (Cr) | J3: EPS (₹) | K3: ROE (%) | L3: ROCE (%) | M3: Notes
A4: TCS | B4: 2223 | C4: 804300 | D4: 361.8 | E4: 0 | F4: 48908 | G4: 255324 | H4: 67407 | I4: 48797 | J4: 134.2 | K4: 51.8 | L4: 63 | M4: NSE:TCS — Tata Consultancy Services
A5: Infosys | B5: 1157 | C5: 469708 | D5: 406 | E5: 0 | F5: 97099 | G5: 162990 | H5: 38921 | I5: 26750 | J5: 64.6 | K5: 35.2 | L5: 39.9 | M5: NSE:INFY — Infosys Ltd
A6: Wipro | B6: 184 | C6: 193749 | D6: 1053 | E6: 20490 | F6: 34500 | G6: 89088 | H6: 18250 | I6: 13218 | J6: 12.63 | K6: 14.9 | L6: 17.8 | M6: NSE:WIPRO — Wipro Ltd
A7: HCL Tech | B7: 1166 | C7: 316630 | D7: 271.6 | E7: 2150 | F7: 11200 | G7: 116180 | H7: 25480 | I7: 15740 | J7: 58.02 | K7: 22.1 | L7: 30.6 | M7: NSE:HCLTECH — HCL Technologies
A8: Mphasis | B8: 2326 | C8: 44419 | D8: 19.1 | E8: 1820 | F8: 2450 | G8: 13496 | H8: 2639 | I8: 1554 | J8: 82.4 | K8: 22.7 | L8: 30.3 | M8: NSE:MPHASIS — Mphasis Ltd
A9: Coforge | B9: 1483 | C9: 63782 | D9: 43 | E9: 1140 | F9: 1350 | G9: 12051 | H9: 1694 | I9: 936 | J9: 24.29 | K9: 20.6 | L9: 23.5 | M9: NSE:COFORGE — Coforge Ltd (growth outlier)

Sheet Multiple Engine
A1: Multiple Engine — Computed EV/Revenue, EV/EBITDA, P/E, P/BV
A2: All formulas pull from Peer Data sheet · Black = formula · No hardcoded values
A3: Company | B3: Net Debt (Cr) | C3: EV (Cr) | D3: EBITDA Margin | E3: PAT Margin | F3: EV/Revenue | G3: EV/EBITDA | H3: P/E | I3: P/BV | J3: BV/Share (₹) | K3: Comment
A4: ='Peer Data'!A4 -> TCS | B4: ='Peer Data'!E4-'Peer Data'!F4 -> -48908 | C4: ='Peer Data'!C4+B4 -> 755392 | D4: ='Peer Data'!H4/'Peer Data'!G4 -> 0.26400573 | E4: ='Peer Data'!I4/'Peer Data'!G4 -> 0.19111795 | F4: =C4/'Peer Data'!G4 -> 2.9585625 | G4: =C4/'Peer Data'!H4 -> 11.206433 | H4: ='Peer Data'!B4/'Peer Data'!J4 -> 16.564829 | I4: ='Peer Data'!B4/J4 -> 8.5377742 | J4: =('Peer Data'!I4/('Peer Data'!K4/100))/'Peer Data'!D4 -> 260.37231
A5: ='Peer Data'!A5 -> Infosys | B5: ='Peer Data'!E5-'Peer Data'!F5 -> -97099 | C5: ='Peer Data'!C5+B5 -> 372609 | D5: ='Peer Data'!H5/'Peer Data'!G5 -> 0.23879379 | E5: ='Peer Data'!I5/'Peer Data'!G5 -> 0.1641205 | F5: =C5/'Peer Data'!G5 -> 2.286085 | G5: =C5/'Peer Data'!H5 -> 9.5734693 | H5: ='Peer Data'!B5/'Peer Data'!J5 -> 17.910217 | I5: ='Peer Data'!B5/J5 -> 6.1812779 | J5: =('Peer Data'!I5/('Peer Data'!K5/100))/'Peer Data'!D5 -> 187.17812
A6: ='Peer Data'!A6 -> Wipro | B6: ='Peer Data'!E6-'Peer Data'!F6 -> -14010 | C6: ='Peer Data'!C6+B6 -> 179739 | D6: ='Peer Data'!H6/'Peer Data'!G6 -> 0.20485363 | E6: ='Peer Data'!I6/'Peer Data'!G6 -> 0.14837015 | F6: =C6/'Peer Data'!G6 -> 2.0175445 | G6: =C6/'Peer Data'!H6 -> 9.8487123 | H6: ='Peer Data'!B6/'Peer Data'!J6 -> 14.568488 | I6: ='Peer Data'!B6/J6 -> 2.1840708 | J6: =('Peer Data'!I6/('Peer Data'!K6/100))/'Peer Data'!D6 -> 84.246353
A7: ='Peer Data'!A7 -> HCL Tech | B7: ='Peer Data'!E7-'Peer Data'!F7 -> -9050 | C7: ='Peer Data'!C7+B7 -> 307580 | D7: ='Peer Data'!H7/'Peer Data'!G7 -> 0.21931486 | E7: ='Peer Data'!I7/'Peer Data'!G7 -> 0.13547943 | F7: =C7/'Peer Data'!G7 -> 2.6474436 | G7: =C7/'Peer Data'!H7 -> 12.071429 | H7: ='Peer Data'!B7/'Peer Data'!J7 -> 20.096518 | I7: ='Peer Data'!B7/J7 -> 4.4464751 | J7: =('Peer Data'!I7/('Peer Data'!K7/100))/'Peer Data'!D7 -> 262.23019
A8: ='Peer Data'!A8 -> Mphasis | B8: ='Peer Data'!E8-'Peer Data'!F8 -> -630 | C8: ='Peer Data'!C8+B8 -> 43789 | D8: ='Peer Data'!H8/'Peer Data'!G8 -> 0.19553942 | E8: ='Peer Data'!I8/'Peer Data'!G8 -> 0.11514523 | F8: =C8/'Peer Data'!G8 -> 3.244591 | G8: =C8/'Peer Data'!H8 -> 16.593028 | H8: ='Peer Data'!B8/'Peer Data'!J8 -> 28.228155 | I8: ='Peer Data'!B8/J8 -> 6.4895999 | J8: =('Peer Data'!I8/('Peer Data'!K8/100))/'Peer Data'!D8 -> 358.41963
A9: ='Peer Data'!A9 -> Coforge | B9: ='Peer Data'!E9-'Peer Data'!F9 -> -210 | C9: ='Peer Data'!C9+B9 -> 63572 | D9: ='Peer Data'!H9/'Peer Data'!G9 -> 0.14056925 | E9: ='Peer Data'!I9/'Peer Data'!G9 -> 0.077669903 | F9: =C9/'Peer Data'!G9 -> 5.2752469 | G9: =C9/'Peer Data'!H9 -> 37.527745 | H9: ='Peer Data'!B9/'Peer Data'!J9 -> 61.053932 | I9: ='Peer Data'!B9/J9 -> 14.03463 | J9: =('Peer Data'!I9/('Peer Data'!K9/100))/'Peer Data'!D9 -> 105.66719 | K9: ⚠ Outlier — significant growth premium
A10: ⚠ Coforge trades at ~37.5x EV/EBITDA — exclude from statistics for conservative analysis.

Sheet Statistics
A1: Multiple Statistics — Full Peer Set & Ex-Coforge
A2: Median row is the key row for implied valuation · Coforge is a growth outlier at ~37.5x EV/EBITDA
A3: FULL PEER SET (n=6) | G3: EX-COFORGE (n=5)
A4: Stat | B4: EV/Revenue | C4: EV/EBITDA | D4: P/E | E4: P/BV | G4: Stat | H4: EV/Revenue | I4: EV/EBITDA | J4: P/E | K4: P/BV
A5: Minimum | B5: =MIN('Multiple Engine'!F4:F9) -> 2.0175445 | C5: =MIN('Multiple Engine'!G4:G9) -> 9.5734693 | D5: =MIN('Multiple Engine'!H4:H9) -> 14.568488 | E5: =MIN('Multiple Engine'!I4:I9) -> 2.1840708 | G5: Minimum | H5: =MIN('Multiple Engine'!F4:F8) -> 2.0175445 | I5: =MIN('Multiple Engine'!G4:G8) -> 9.5734693 | J5: =MIN('Multiple Engine'!H4:H8) -> 14.568488 | K5: =MIN('Multiple Engine'!I4:I8) -> 2.1840708
A6: 25th Percentile | B6: =PERCENTILE('Multiple Engine'!F4:F9,0.25) -> 2.3764247 | C6: =PERCENTILE('Multiple Engine'!G4:G9,0.25) -> 10.188142 | D6: =PERCENTILE('Multiple Engine'!H4:H9,0.25) -> 16.901176 | E6: =PERCENTILE('Multiple Engine'!I4:I9,0.25) -> 4.8801758 | G6: 25th Percentile | H6: =PERCENTILE('Multiple Engine'!F4:F8,0.25) -> 2.286085 | I6: =PERCENTILE('Multiple Engine'!G4:G8,0.25) -> 9.8487123 | J6: =PERCENTILE('Multiple Engine'!H4:H8,0.25) -> 16.564829 | K6: =PERCENTILE('Multiple Engine'!I4:I8,0.25) -> 4.4464751
A7: Median | B7: =MEDIAN('Multiple Engine'!F4:F9) -> 2.803003 | C7: =MEDIAN('Multiple Engine'!G4:G9) -> 11.638931 | D7: =MEDIAN('Multiple Engine'!H4:H9) -> 19.003368 | E7: =MEDIAN('Multiple Engine'!I4:I9) -> 6.3354389 | G7: Median | H7: =MEDIAN('Multiple Engine'!F4:F8) -> 2.6474436 | I7: =MEDIAN('Multiple Engine'!G4:G8) -> 11.206433 | J7: =MEDIAN('Multiple Engine'!H4:H8) -> 17.910217 | K7: =MEDIAN('Multiple Engine'!I4:I8) -> 6.1812779
A8: Mean | B8: =AVERAGE('Multiple Engine'!F4:F9) -> 3.0715789 | C8: =AVERAGE('Multiple Engine'!G4:G9) -> 16.136803 | D8: =AVERAGE('Multiple Engine'!H4:H9) -> 26.40369 | E8: =AVERAGE('Multiple Engine'!I4:I9) -> 6.9789714 | G8: Mean | H8: =AVERAGE('Multiple Engine'!F4:F8) -> 2.6308453 | I8: =AVERAGE('Multiple Engine'!G4:G8) -> 11.858614 | J8: =AVERAGE('Multiple Engine'!H4:H8) -> 19.473641 | K8: =AVERAGE('Multiple Engine'!I4:I8) -> 5.5678396
A9: 75th Percentile | B9: =PERCENTILE('Multiple Engine'!F4:F9,0.75) -> 3.1730839 | C9: =PERCENTILE('Multiple Engine'!G4:G9,0.75) -> 15.462628 | D9: =PERCENTILE('Multiple Engine'!H4:H9,0.75) -> 26.195246 | E9: =PERCENTILE('Multiple Engine'!I4:I9,0.75) -> 8.0257306 | G9: 75th Percentile | H9: =PERCENTILE('Multiple Engine'!F4:F8,0.75) -> 2.9585625 | I9: =PERCENTILE('Multiple Engine'!G4:G8,0.75) -> 12.071429 | J9: =PERCENTILE('Multiple Engine'!H4:H8,0.75) -> 20.096518 | K9: =PERCENTILE('Multiple Engine'!I4:I8,0.75) -> 6.4895999
A10: Maximum | B10: =MAX('Multiple Engine'!F4:F9) -> 5.2752469 | C10: =MAX('Multiple Engine'!G4:G9) -> 37.527745 | D10: =MAX('Multiple Engine'!H4:H9) -> 61.053932 | E10: =MAX('Multiple Engine'!I4:I9) -> 14.03463 | G10: Maximum | H10: =MAX('Multiple Engine'!F4:F8) -> 3.244591 | I10: =MAX('Multiple Engine'!G4:G8) -> 16.593028 | J10: =MAX('Multiple Engine'!H4:H8) -> 28.228155 | K10: =MAX('Multiple Engine'!I4:I8) -> 8.5377742
A11: Median row (highlighted navy) = the key row applied in Implied Valuation. Use ex-Coforge for conservative analysis.

Sheet Target
A1: Target Company — Meridian Digital Ltd (Fictional)
A2: Fictional mid-tier Indian IT services · B2B digital transformation, cloud, AI services · Blue = change these
A3: TARGET FINANCIALS | B3: Value | C3: Notes
A4: Company Name | B4: Meridian Digital Ltd
A5: Share Price (₹) | B5: 875
A6: Shares Outstanding (Cr) | B6: 35
A7: Market Cap (₹ Cr) | B7: =B5*B6 -> 30625 | C7: Price × Shares
A8: Debt (₹ Cr) | B8: 500
A9: Cash (₹ Cr) | B9: 1200
A10: Net Debt (₹ Cr) | B10: =B8-B9 -> -700 | C10: Debt − Cash (neg = net cash)
A11: Enterprise Value (₹ Cr) | B11: =B7+B10 -> 29925 | C11: Market Cap + Net Debt
A12: Revenue (₹ Cr) | B12: 8500
A13: EBITDA (₹ Cr) | B13: 1530
A14: EBITDA Margin | B14: =B13/B12 -> 0.18 | C14: EBITDA / Revenue
A15: PAT (₹ Cr) | B15: 950
A16: PAT Margin | B16: =B15/B12 -> 0.11176471 | C16: PAT / Revenue
A17: EPS (₹) | B17: 27.14
A18: ROE (%) | B18: 19.5
A19: ROCE (%) | B19: 25.8
A20: Book Value / Share (₹) | B20: =(B15/(B18/100))/B6 -> 139.19414 | C20: (PAT / ROE%) / Shares

Sheet Implied Valuation
A1: Implied Valuation — 4-Method Analysis
A2: Uses MEDIAN from Statistics sheet · Change target inputs in Target sheet · Both full & ex-Coforge shown
A3: Method | B3: Multiple Used | C3: Implied EV (₹ Cr) | D3: Implied Equity (₹ Cr) | E3: Implied Price (₹) | F3: Current Price (₹) | G3: Upside / Downside
A4: EV / Revenue | B4: =Statistics!B7 -> 2.803003 | C4: =Statistics!B7*Target!B12 -> 23825.526 | D4: =C4-(Target!B10) -> 24525.526 | E4: =D4/Target!B6 -> 700.72931 | F4: =Target!B5 -> 875 | G4: =E4/F4-1 -> -0.1991665
A5: EV / EBITDA | B5: =Statistics!C7 -> 11.638931 | C5: =Statistics!C7*Target!B13 -> 17807.564 | D5: =C5-(Target!B10) -> 18507.564 | E5: =D5/Target!B6 -> 528.78754 | F5: =Target!B5 -> 875 | G5: =E5/F5-1 -> -0.39567139
A6: P / E | B6: =Statistics!D7 -> 19.003368 | C6: =Target!B17*Statistics!D7*Target!B6+(Target!B10) -> 17351.299 | D6: =Target!B17*Statistics!D7*Target!B6 -> 18051.299 | E6: =Target!B17*Statistics!D7 -> 515.7514 | F6: =Target!B5 -> 875 | G6: =E6/F6-1 -> -0.41056983
A7: P / Book Value | B7: =Statistics!E7 -> 6.3354389 | C7: =Target!B20*Target!B6*Statistics!E7+(Target!B10) -> 30164.959 | D7: =Target!B20*Target!B6*Statistics!E7 -> 30864.959 | E7: =Target!B20*Statistics!E7 -> 881.85596 | F7: =Target!B5 -> 875 | G7: =E7/F7-1 -> 0.0078353858
A9: SUMMARY — MEDIAN OF METHODS
A10: Metric | B10: Implied Price (₹) | C10: vs Current | D10: Verdict
A11: Floor (Minimum method) | B11: =MIN(E4:E7) -> 515.7514 | C11: =B11/Target!B5-1 -> -0.41056983 | D11: Most conservative
A12: Median of Methods | B12: =MEDIAN(E4:E7) -> 614.75842 | C12: =B12/Target!B5-1 -> -0.29741895 | D12: Key midpoint — use this
A13: Ceiling (Maximum method) | B13: =MAX(E4:E7) -> 881.85596 | C13: =B13/Target!B5-1 -> 0.0078353858 | D13: Most optimistic
A14: Current Market Price | B14: =Target!B5 -> 875 | D14: Market consensus
A16: FOOTBALL FIELD — PRICE RANGE BY METHOD (Median Stats)
A17: Method | B17: Min (₹) | C17: 25th Pct (₹) | D17: Median (₹) | E17: 75th Pct (₹) | F17: Max (₹) | G17: Current (₹)
A18: EV / Revenue | B18: =(Statistics!B5*Target!B12-(Target!B10))/Target!B6 -> 509.97508 | C18: =(Statistics!B6*Target!B12-(Target!B10))/Target!B6 -> 597.13171 | D18: =(Statistics!B7*Target!B12-(Target!B10))/Target!B6 -> 700.72931 | E18: =(Statistics!B9*Target!B12-(Target!B10))/Target!B6 -> 790.60608 | F18: =(Statistics!B10*Target!B12-(Target!B10))/Target!B6 -> 1301.1314 | G18: =Target!B5 -> 875
A19: EV / EBITDA | B19: =(Statistics!C5*Target!B13-(Target!B10))/Target!B6 -> 438.49737 | C19: =(Statistics!C6*Target!B13-(Target!B10))/Target!B6 -> 465.36737 | D19: =(Statistics!C7*Target!B13-(Target!B10))/Target!B6 -> 528.78754 | E19: =(Statistics!C9*Target!B13-(Target!B10))/Target!B6 -> 695.93773 | F19: =(Statistics!C10*Target!B13-(Target!B10))/Target!B6 -> 1660.4986 | G19: =Target!B5 -> 875
A20: P / E | B20: =Statistics!D5*Target!B17 -> 395.38876 | C20: =Statistics!D6*Target!B17 -> 458.69791 | D20: =Statistics!D7*Target!B17 -> 515.7514 | E20: =Statistics!D9*Target!B17 -> 710.93898 | F20: =Statistics!D10*Target!B17 -> 1657.0037 | G20: =Target!B5 -> 875
A21: P / Book Value | B21: =Statistics!E5*Target!B20 -> 304.00986 | C21: =Statistics!E6*Target!B20 -> 679.29187 | D21: =Statistics!E7*Target!B20 -> 881.85596 | E21: =Statistics!E9*Target!B20 -> 1117.1347 | F21: =Statistics!E10*Target!B20 -> 1953.5383 | G21: =Target!B5 -> 875
A23: CompsDesk · Day 19 · 30 Days of AI Finance · Peer data FY25 verified · Meridian Digital Ltd is fictional · Not investment advice.
